mglcmdtools
